{
  "shipper": "趋势网络有限公司",
  "consignee": "Sherman and Sons",
  "notify_party": "Hamilton Ltd",
  "bl_no": "BL07701815",
  "pol": "NINGBO",
  "pod": "HAIPHONG",
  "vessel": "ONE HARBOUR",
  "voyage": "708S",
  "por": "NINGBO",
  "delivery": "HAMBURG",
  "container1": "EVER6388711",
  "seal1": "SL-THABNQ84",
  "container2": "EVER5374533",
  "seal2": "SL-4B0QS1TE",
  "qty1": "129",
  "pkg1": "CARTONS",
  "qty2": "119",
  "pkg2": "CARTONS",
  "desc1": "SEAMLESS EXPLICIT LEVERAGE / 的是",
  "desc2": "ERGONOMIC ECO-CENTRIC THROUGHPUT / 你们",
  "gw1": "16759",
  "cbm1": "56.49",
  "gw2": "7316",
  "cbm2": "42.38",
  "total_gw": "24075",
  "total_cbm": "98.87",
  "freight": "PREPAID",
  "issue_place": "SHENZHEN",
  "issue_date": "06/06/2024",
  "template": "cosco_style"
}